limoon/__about__.py
limoon/__init__.py
limoon/constants.py
limoon/core.py
limoon/exceptions.py
limoon/models.py
limoon/utils.py
limoon-0.1.12.dist-info/METADATA
limoon-0.1.12.dist-info/WHEEL
limoon-0.1.12.dist-info/licenses/LICENSE.txt
limoon-0.1.12.dist-info/RECORD
