Metadata-Version: 2.4
Name: limoon
Version: 0.1.12
Summary: Web scraper base Pythonic API for Ekşi Sözlük
Project-URL: Source, https://github.com/beucismis/limoon
Project-URL: Issues, https://github.com/beucismis/limoon/issues
Project-URL: Documentation, https://github.com/beucismis/limoon/DOCUMENTATION.md
Author-email: beucismis <beucismis@tutamail.com>
License-Expression: MIT
License-File: LICENSE.txt
Classifier: Development Status :: 4 - Beta
Classifier: Programming Language :: Python
Classifier: Programming Language :: Python :: 3.9
Classifier: Programming Language :: Python :: 3.10
Classifier: Programming Language :: Python :: 3.11
Classifier: Programming Language :: Python :: 3.12
Classifier: Programming Language :: Python :: Implementation :: CPython
Classifier: Programming Language :: Python :: Implementation :: PyPy
Requires-Python: >=3.9
Requires-Dist: curl-adapter==1.1.0
Requires-Dist: fake-useragent==2.2.0
Requires-Dist: lxml-html-clean==0.4.2
Requires-Dist: requests-html==0.10.0
